{
  "hash": "4267c561",
  "configHash": "f7c280e5",
  "lockfileHash": "5810feda",
  "browserHash": "a038d4b9",
  "optimized": {
    "vue": {
      "src": "../../../../node_modules/vue/dist/vue.runtime.esm-bundler.js",
      "file": "vue.js",
      "fileHash": "7d52e6b4",
      "needsInterop": false
    },
    "vitepress > @vue/devtools-api": {
      "src": "../../../../node_modules/@vue/devtools-api/dist/index.js",
      "file": "vitepress___@vue_devtools-api.js",
      "fileHash": "f1013e69",
      "needsInterop": false
    },
    "vitepress > @vueuse/core": {
      "src": "../../../../node_modules/@vueuse/core/index.mjs",
      "file": "vitepress___@vueuse_core.js",
      "fileHash": "e81c4d19",
      "needsInterop": false
    },
    "vue-easy-lightbox": {
      "src": "../../../../node_modules/vue-easy-lightbox/dist/vue-easy-lightbox.esm.min.js",
      "file": "vue-easy-lightbox.js",
      "fileHash": "367ca3f9",
      "needsInterop": false
    },
    "swiper/vue": {
      "src": "../../../../node_modules/swiper/swiper-vue.mjs",
      "file": "swiper_vue.js",
      "fileHash": "2f383ed5",
      "needsInterop": false
    },
    "markdown-it": {
      "src": "../../../../node_modules/markdown-it/index.mjs",
      "file": "markdown-it.js",
      "fileHash": "84e6a33c",
      "needsInterop": false
    },
    "jspdf": {
      "src": "../../../../node_modules/jspdf/dist/jspdf.es.min.js",
      "file": "jspdf.js",
      "fileHash": "c3a7936d",
      "needsInterop": false
    },
    "docx": {
      "src": "../../../../node_modules/docx/dist/index.mjs",
      "file": "docx.js",
      "fileHash": "f8a142b7",
      "needsInterop": false
    },
    "file-saver": {
      "src": "../../../../node_modules/file-saver/dist/FileSaver.min.js",
      "file": "file-saver.js",
      "fileHash": "451b0f30",
      "needsInterop": true
    },
    "pdfmake/build/pdfmake": {
      "src": "../../../../node_modules/pdfmake/build/pdfmake.js",
      "file": "pdfmake_build_pdfmake.js",
      "fileHash": "f047dce9",
      "needsInterop": true
    },
    "pdfmake/build/vfs_fonts": {
      "src": "../../../../node_modules/pdfmake/build/vfs_fonts.js",
      "file": "pdfmake_build_vfs_fonts.js",
      "fileHash": "d83a6f7b",
      "needsInterop": true
    }
  },
  "chunks": {
    "html2canvas.esm-T2B2HELW": {
      "file": "html2canvas__esm-T2B2HELW.js"
    },
    "purify.es-OAQKXHAP": {
      "file": "purify__es-OAQKXHAP.js"
    },
    "index.es-T5X3BX5E": {
      "file": "index__es-T5X3BX5E.js"
    },
    "chunk-LW4I4DCF": {
      "file": "chunk-LW4I4DCF.js"
    },
    "chunk-2ALL2YQY": {
      "file": "chunk-2ALL2YQY.js"
    },
    "chunk-G3PMV62Z": {
      "file": "chunk-G3PMV62Z.js"
    }
  }
}